sstc_utils/__init__.py
sstc_utils/decorators.py
sstc_utils/requirements.txt
sstc_utils/utils.py
sstc_utils/version.py
sstc_utils-0.1.2.dist-info/METADATA
sstc_utils-0.1.2.dist-info/WHEEL
sstc_utils-0.1.2.dist-info/RECORD
