Metadata-Version: 2.1
Name: sstc-utils
Version: 0.1.2
Summary: 
Author: Jobelund
Author-email: 124563223+jobelund@users.noreply.github.com
Requires-Python: >=3.11,<4.0
Classifier: Programming Language :: Python :: 3
Classifier: Programming Language :: Python :: 3.11
Classifier: Programming Language :: Python :: 3.12
Requires-Dist: mkdocs
Requires-Dist: mkdocs-rtd-dropdown
Requires-Dist: mkdocstrings-python
Requires-Dist: pyexiv2
Requires-Dist: pytest
Requires-Dist: pyyaml
